---
title: Java 虚拟机指令操作码和助记符映射关系
tags: [JVM]
categories: [JVM]
date: 2024-06-25 18:50:22
updated: 2024-06-26 8:00:00
cover: /assets/cover/jvm.png
banner: /assets/banner/banner_9.jpg
topic: jvm
references:
  - '[Chapter 7. Opcode Mnemonics by Opcode](https://docs.oracle.com/javase/specs/jvms/se21/html/jvms-7.html)'
---

## 前言

本文整理了 **Java 虚拟机指令操作码和助记符之间的映射关系**，可以用于日常学习 Java 字节码时快速查阅。需要注意的是，操作码 `186` 对应的 `invokedynamic` 指令是 JDK 7 版本新增的指令，在 JDK 7 之前的版本没有该指令。

## 常量 Constants

| 字节码（十进制） | 字节码（十六进制） | 助记符      | 指令含义                                                     |
| ---------------- | ------------------ | ----------- | ------------------------------------------------------------ |
| 00               | 0x00               | nop         | 无操作                                                       |
| 01               | 0x01               | aconst_null | 将 null 推至栈顶                                             |
| 02               | 0x02               | iconst_m1   | 将 int 型 -1 推至栈顶                                        |
| 03               | 0x03               | iconst_0    | 将 int 型 0 推至栈顶                                         |
| 04               | 0x04               | iconst_1    | 将 int 型 1 推至栈顶                                         |
| 05               | 0x05               | iconst_2    | 将 int 型 2 推至栈顶                                         |
| 06               | 0x06               | iconst_3    | 将 int 型 3 推至栈顶                                         |
| 07               | 0x07               | iconst_4    | 将 int 型 4 推至栈顶                                         |
| 08               | 0x08               | iconst_5    | 将 int 型 5 推至栈顶                                         |
| 09               | 0x09               | lconst_0    | 将 long 型 0 推至栈顶                                        |
| 10               | 0x0a               | lconst_1    | 将 long 型 1 推至栈顶                                        |
| 11               | 0x0b               | fconst_0    | 将 float 型 0 推至栈顶                                       |
| 12               | 0x0c               | fconst_1    | 将 float 型 1 推至栈顶                                       |
| 13               | 0x0d               | fconst_2    | 将 float 型 2 推至栈顶                                       |
| 14               | 0x0e               | dconst_0    | 将 double 型 0 推至栈顶                                      |
| 15               | 0x0f               | dconst_1    | 将 double 型 1 推至栈顶                                      |
| 16               | 0x10               | bipush      | 将单字节的常量值（-128~127）推至栈顶                         |
| 17               | 0x11               | sipush      | 将一个短整型常量（-32768~32767）推至栈顶                     |
| 18               | 0x12               | ldc         | 将 int，float 或 String 型常量值从常量池中推至栈顶           |
| 19               | 0x13               | ldc_w       | 将 int，float 或 String 型常量值从常量池中推至栈顶（宽索引） |
| 20               | 0x14               | ldc2_w      | 将 long 或 double 型常量值从常量池中推至栈顶（宽索引）       |

## 加载 Loads

| 字节码（十进制） | 字节码（十六进制） | 助记符  | 指令含义                                      |
| ---------------- | ------------------ | ------- | --------------------------------------------- |
| 21               | 0x15               | iload   | 将指定的 int 型本地变量推至栈顶               |
| 22               | 0x16               | lload   | 将指定的 long 型本地变量推至栈顶              |
| 23               | 0x17               | fload   | 将指定的 float 型本地变量推至栈顶             |
| 24               | 0x18               | dload   | 将指定的 double 型本地变量推至栈顶            |
| 25               | 0x19               | aload   | 将指定的引用类型本地变量推至栈顶              |
| 26               | 0x1a               | iload_0 | 将第一个 int 型本地变量推至栈顶               |
| 27               | 0x1b               | iload_1 | 将第二个 int 型本地变量推至栈顶               |
| 28               | 0x1c               | iload_2 | 将第三个 int 型本地变量推至栈顶               |
| 29               | 0x1d               | iload_3 | 将第四个 int 型本地变量推至栈顶               |
| 30               | 0x1e               | lload_0 | 将第一个 long 型本地变量推至栈顶              |
| 31               | 0x1f               | lload_1 | 将第二个 long 型本地变量推至栈顶              |
| 32               | 0x20               | lload_2 | 将第三个 long 型本地变量推至栈顶              |
| 33               | 0x21               | lload_3 | 将第四个 long 型本地变量推至栈顶              |
| 34               | 0x22               | fload_0 | 将第一个 float 型本地变量推至栈顶             |
| 35               | 0x23               | fload_1 | 将第二个 float 型本地变量推至栈顶             |
| 36               | 0x24               | fload_2 | 将第三个 float 型本地变量推至栈顶             |
| 37               | 0x25               | fload_3 | 将第四个 float 型本地变量推至栈顶             |
| 38               | 0x26               | dload_0 | 将第一个 double 型本地变量推至栈顶            |
| 39               | 0x27               | dload_1 | 将第二个 double 型本地变量推至栈顶            |
| 40               | 0x28               | dload_2 | 将第三个 double 型本地变量推至栈顶            |
| 41               | 0x29               | dload_3 | 将第四个 double 型本地变量推至栈顶            |
| 42               | 0x2a               | aload_0 | 将第一个引用类型本地变量推至栈顶              |
| 43               | 0x2b               | aload_1 | 将第二个引用类型本地变量推至栈顶              |
| 44               | 0x2c               | aload_2 | 将第三个引用类型本地变量推至栈顶              |
| 45               | 0x2d               | aload_3 | 将第四个引用类型本地变量推至栈顶              |
| 46               | 0x2e               | iaload  | 将 int 型数组指定索引的值推至栈顶             |
| 47               | 0x2f               | laload  | 将 long 型数组指定索引的值推至栈顶            |
| 48               | 0x30               | faload  | 将 float 型数组指定索引的值推至栈顶           |
| 49               | 0x31               | daload  | 将 double 型数组指定索引的值推至栈顶          |
| 50               | 0x32               | aaload  | 将引用类型数组指定索引的值推至栈顶            |
| 51               | 0x33               | baload  | 将 boolean 或 byte 型数组指定索引的值推至栈顶 |
| 52               | 0x34               | caload  | 将 char 型数组指定索引的值推至栈顶            |
| 53               | 0x35               | saload  | 将 short 型数组指定索引的值推至栈顶           |

## 存储 Stores

| 字节码（十进制） | 字节码（十六进制） | 助记符   | 指令含义                                                |
| ---------------- | ------------------ | -------- | ------------------------------------------------------- |
| 54               | 0x36               | istore   | 将栈顶 int 型数值存入指定本地变量                       |
| 55               | 0x37               | lstore   | 将栈顶 long 型数值存入指定本地变量                      |
| 56               | 0x38               | fstore   | 将栈顶 float 型数值存入指定本地变量                     |
| 57               | 0x39               | dstore   | 将栈顶 double 型数值存入指定本地变量                    |
| 58               | 0x3a               | astore   | 将栈顶引用类型数值存入指定本地变量                      |
| 59               | 0x3b               | istore_0 | 将栈顶 int 型数值存入第一个本地变量                     |
| 60               | 0x3c               | istore_1 | 将栈顶 int 型数值存入第二个本地变量                     |
| 61               | 0x3d               | istore_2 | 将栈顶 int 型数值存入第三个本地变量                     |
| 62               | 0x3e               | istore_3 | 将栈顶 int 型数值存入第四个本地变量                     |
| 63               | 0x3f               | lstore_0 | 将栈顶 long 型数值存入第一个本地变量                    |
| 64               | 0x40               | lstore_1 | 将栈顶 long 型数值存入第二个本地变量                    |
| 65               | 0x41               | lstore_2 | 将栈顶 long 型数值存入第三个本地变量                    |
| 66               | 0x42               | lstore_3 | 将栈顶 long 型数值存入第四个本地变量                    |
| 67               | 0x43               | fstore_0 | 将栈顶 float 型数值存入第一个本地变量                   |
| 68               | 0x44               | fstore_1 | 将栈顶 float 型数值存入第二个本地变量                   |
| 69               | 0x45               | fstore_2 | 将栈顶 float 型数值存入第三个本地变量                   |
| 70               | 0x46               | fstore_3 | 将栈顶 float 型数值存入第四个本地变量                   |
| 71               | 0x47               | dstore_0 | 将栈顶 double 型数值存入第一个本地变量                  |
| 72               | 0x48               | dstore_1 | 将栈顶 double 型数值存入第二个本地变量                  |
| 73               | 0x49               | dstore_2 | 将栈顶 double 型数值存入第三个本地变量                  |
| 74               | 0x4a               | dstore_3 | 将栈顶 double 型数值存入第四个本地变量                  |
| 75               | 0x4b               | astore_0 | 将栈顶引用型数值存入第一个本地变量                      |
| 76               | 0x4c               | astore_1 | 将栈顶引用型数值存入第二个本地变量                      |
| 77               | 0x4d               | astore_2 | 将栈顶引用型数值存入第三个本地变量                      |
| 78               | 0x4e               | astore_3 | 将栈顶引用型数值存入第四个本地变量                      |
| 79               | 0x4f               | iastore  | 将栈顶 int 型数值存入指定数组的指定索引位置             |
| 80               | 0x50               | lastore  | 将栈顶 long 型数值存入指定数组的指定索引位置            |
| 81               | 0x51               | fastore  | 将栈顶 float 型数值存入指定数组的指定索引位置           |
| 82               | 0x52               | dastore  | 将栈顶 double 型数值存入指定数组的指定索引位置          |
| 83               | 0x53               | aastore  | 将栈顶引用型数值存入指定数组的指定索引位置              |
| 84               | 0x54               | bastore  | 将栈顶 boolean 或 byte 型数值存入指定数组的指定索引位置 |
| 85               | 0x55               | castore  | 将栈顶 char 型数值存入指定数组的指定索引位置            |
| 86               | 0x56               | sastore  | 将栈顶 short 型数值存入指定数组的指定索引位置           |

## 栈操作 Stack

| 字节码（十进制） | 字节码（十六进制） | 助记符  | 指令含义                                                     |
| ---------------- | ------------------ | ------- | ------------------------------------------------------------ |
| 87               | 0x57               | pop     | 将栈顶数值弹出（数值不能是 long 或 double 类型的）           |
| 88               | 0x58               | pop2    | 将栈顶的一个（对于非 long 或 double 类型）或两个数值（对于非 long 或 double 的其他类型）弹出 |
| 89               | 0x59               | dup     | 复制栈顶数值并将复制值压入栈顶                               |
| 90               | 0x5a               | dup_x1  | 复制栈顶数值并将两个复制值压入栈顶                           |
| 91               | 0x5b               | dup_x2  | 复制栈顶数值并将三个（或两个）复制值压入栈顶                 |
| 92               | 0x5c               | dup2    | 复制栈顶一个（对于 long 或 double 类型）或两个（对于非 long 或 double 的其他类型）数值并将复制值压入栈顶 |
| 93               | 0x5d               | dup2_x1 | dup_x1 指令的双倍版本                                        |
| 94               | 0x5e               | dup2_x2 | dup_x2 指令的双倍版本                                        |
| 95               | 0x5f               | swap    | 将栈顶最顶端的两个数值互换（数值不能是 long 或 double 类型） |

## 数学运算 Math

| 字节码（十进制） | 字节码（十六进制） | 助记符 | 指令含义                                             |
| ---------------- | ------------------ | ------ | ---------------------------------------------------- |
| 96               | 0x60               | iadd   | 将栈顶两 int 型数值相加并将结果压入栈顶              |
| 97               | 0x61               | ladd   | 将栈顶两 long 型数值相加并将结果压入栈顶             |
| 98               | 0x62               | fadd   | 将栈顶两 float 型数值相加并将结果压入栈顶            |
| 99               | 0x63               | dadd   | 将栈顶两 double 型数值相加并将结果压入栈顶           |
| 100              | 0x64               | isub   | 将栈顶两 int 型数值相减并将结果压入栈顶              |
| 101              | 0x65               | lsub   | 将栈顶两 long 型数值相减并将结果压入栈顶             |
| 102              | 0x66               | fsub   | 将栈顶两 float 型数值相减并将结果压入栈顶            |
| 103              | 0x67               | dsub   | 将栈顶两 double 型数值相减并将结果压入栈顶           |
| 104              | 0x68               | imul   | 将栈顶两 int 型数值相乘并将结果压入栈顶              |
| 105              | 0x69               | lmul   | 将栈顶两 long 型数值相乘并将结果压入栈顶             |
| 106              | 0x6a               | fmul   | 将栈顶两 float 型数值相乘并将结果压入栈顶            |
| 107              | 0x6b               | dmul   | 将栈顶两 double 型数值相乘并将结果压入栈顶           |
| 108              | 0x6c               | idiv   | 将栈顶两 int 型数值相除并将结果压入栈顶              |
| 109              | 0x6d               | ldiv   | 将栈顶两 long 型数值相除并将结果压入栈顶             |
| 110              | 0x6e               | fdiv   | 将栈顶两 float 型数值相除并将结果压入栈顶            |
| 111              | 0x6f               | ddiv   | 将栈顶两 double 型数值相除并将结果压入栈顶           |
| 112              | 0x70               | irem   | 将栈顶两 int 型数值作取模运算并将结果压入栈顶        |
| 113              | 0x71               | lrem   | 将栈顶两 long 型数值作取模运算并将结果压入栈顶       |
| 114              | 0x72               | frem   | 将栈顶两 float 型数值作取模运算并将结果压入栈顶      |
| 115              | 0x73               | drem   | 将栈顶两 double 型数值作取模运算并将结果压入栈顶     |
| 116              | 0x74               | ineg   | 将栈顶 int 型数值取负并将结果压入栈顶                |
| 117              | 0x75               | lneg   | 将栈顶 long 型数值取负并将结果压入栈顶               |
| 118              | 0x76               | fneg   | 将栈顶 float 型数值取负并将结果压入栈顶              |
| 119              | 0x77               | dneg   | 将栈顶 double 型数值取负并将结果压入栈顶             |
| 120              | 0x78               | ishl   | 将 int 型数值左移指定位数并将结果压入栈顶            |
| 121              | 0x79               | lshl   | 将 long 型数值左移指定位数并将结果压入栈顶           |
| 122              | 0x7a               | ishr   | 将 int 型数值右（带符号）移指定位数并将结果压入栈顶  |
| 123              | 0x7b               | lshr   | 将 long 型数值右（带符号）移指定位数并将结果压入栈顶 |
| 124              | 0x7c               | iushr  | 将 int 型数值右（无符号）移指定位数并将结果压入栈顶  |
| 125              | 0x7d               | lushr  | 将 long 型数值右（无符号）移指定位数并将结果压入栈顶 |
| 126              | 0x7e               | iand   | 将栈顶两 int 型数值`按位与`并将结果压入栈顶          |
| 127              | 0x7f               | land   | 将栈顶两 long 型数值`按位与`并将结果压入栈顶         |
| 128              | 0x80               | ior    | 将栈顶两 int 型数值`按位或`并将结果压入栈顶          |
| 129              | 0x81               | lor    | 将栈顶两 long 型数值`按位或`并将结果压入栈顶         |
| 130              | 0x82               | ixor   | 将栈顶两 int 型数值`按位异或`并将结果压入栈顶        |
| 131              | 0x83               | lxor   | 将栈顶两 long 型数值`按位异或`并将结果压入栈顶       |
| 132              | 0x84               | iinc   | 将指定 int 型变量增加指定值（如 i++，i--，i+=2 等）  |

## 转换 Conversions

| 字节码（十进制） | 字节码（十六进制） | 助记符 | 指令含义                                                    |
| ---------------- | ------------------ | ------ | ----------------------------------------------------------- |
| 133              | 0x85               | i2l    | 将栈顶 int 型数值强制转换为 long 型数值并将结果压入栈顶     |
| 134              | 0x86               | i2f    | 将栈顶 int 型数值强制转换为 float 型数值并将结果压入栈顶    |
| 135              | 0x87               | i2d    | 将栈顶 int 型数值强制转换为 double 型数值并将结果压入栈顶   |
| 136              | 0x88               | l2i    | 将栈顶 long 型数值强制转换为 int 型数值并将结果压入栈顶     |
| 137              | 0x89               | l2f    | 将栈顶 long 型数值强制转换为 float 型数值并将结果压入栈顶   |
| 138              | 0x8a               | l2d    | 将栈顶 long 型数值强制转换为 double 型数值并将结果压入栈顶  |
| 139              | 0x8b               | f2i    | 将栈顶 float 型数值强制转换为 int 型数值并将结果压入栈顶    |
| 140              | 0x8c               | f2l    | 将栈顶 float 型数值强制转换为 long 型数值并将结果压入栈顶   |
| 141              | 0x8d               | f2d    | 将栈顶 float 型数值强制转换为 double 型数值并将结果压入栈顶 |
| 142              | 0x8e               | d2i    | 将栈顶 double 型数值强制转换为 int 型数值并将结果压入栈顶   |
| 143              | 0x8f               | d2l    | 将栈顶 double 型数值强制转换为 long 型数值并将结果压入栈顶  |
| 144              | 0x90               | d2f    | 将栈顶 double 型数值强制转换为 float 型数值并将结果压入栈顶 |
| 145              | 0x91               | i2b    | 将栈顶 int 型数值强制转换为 byte 型数值并将结果压入栈顶     |
| 146              | 0x92               | i2c    | 将栈顶 int 型数值强制转换为 char 型数值并将结果压入栈顶     |
| 147              | 0x93               | i2s    | 将栈顶 int 型数值强制转换为 short 型数值并将结果压入栈顶    |

## 比较 Comparisons

| 字节码（十进制） | 字节码（十六进制） | 助记符    | 指令含义                                                     |
| ---------------- | ------------------ | --------- | ------------------------------------------------------------ |
| 148              | 0x94               | lcmp      | 比较栈顶两 long 型数值大小，并将结果（1，0 或 -1）压入栈顶   |
| 149              | 0x95               | fcmpl     | 比较栈顶两 float 型数值大小，并将结果（1，0 或 -1）压入栈顶; 当其中一个数值为 NaN 时，将 -1 压入栈顶 |
| 150              | 0x96               | fcmpg     | 比较栈顶两 float 型数值大小，并将结果（1，0 或 -1）压入栈顶; 当其中一个数值为 NaN 时，将 1 压入栈顶 |
| 151              | 0x97               | dcmpl     | 比较栈顶两 double 型数值大小，并将结果（1，0 或 -1）压入栈顶; 当其中一个数值为 NaN 时，将 -1 压入栈顶 |
| 152              | 0x98               | dcmpg     | 比较栈顶两 double 型数值大小，并将结果（1，0 或 -1）压入栈顶; 当其中一个数值为 NaN 时，将 1 压入栈顶 |
| 153              | 0x99               | ifeq      | 当栈顶 int 型数值等于 0 时跳转                               |
| 154              | 0x9a               | ifne      | 当栈顶 int 型数值不等于 0 时跳转                             |
| 155              | 0x9b               | iflt      | 当栈顶 int 型数值小于 0 时跳转                               |
| 156              | 0x9c               | ifge      | 当栈顶 int 型数值大于等于 0 时跳转                           |
| 157              | 0x9d               | ifgt      | 当栈顶 int 型数值大于 0 时跳转                               |
| 158              | 0x9e               | ifle      | 当栈顶 int 型数值小于等于 0 时跳转                           |
| 159              | 0x9f               | if_icmpeq | 比较栈顶两 int 型数值大小，当结果等于 0 时跳转               |
| 160              | 0xa0               | if_icmpne | 比较栈顶两 int 型数值大小，当结果不等于 0 时跳转             |
| 161              | 0xa1               | if_icmplt | 比较栈顶两 int 型数值大小，当结果小于 0 时跳转               |
| 162              | 0xa2               | if_icmpge | 比较栈顶两 int 型数值大小，当结果大于等于 0 时跳转           |
| 163              | 0xa3               | if_icmpgt | 比较栈顶两 int 型数值大小，当结果大于 0 时跳转               |
| 164              | 0xa4               | if_icmple | 比较栈顶两 int 型数值大小，当结果小于等于 0 时跳转           |
| 165              | 0xa5               | if_acmpeq | 比较栈顶两引用型数值，当结果相等时跳转                       |
| 166              | 0xa6               | if_acmpne | 比较栈顶两引用型数值，当结果不相等时跳转                     |

## 控制 Control

| 字节码（十进制） | 字节码（十六进制） | 助记符       | 指令含义                                                     |
| ---------------- | ------------------ | ------------ | ------------------------------------------------------------ |
| 167              | 0xa7               | goto         | 无条件跳转                                                   |
| 168              | 0xa8               | jsr          | 跳转至指定的 16 位 offset 位置，并将 jsr 的下一条指令地址压入栈顶 |
| 169              | 0xa9               | ret          | 返回至本地变量指定的 index 的指令位置（一般与 jsr 或 jsr_w 联合使用） |
| 170              | 0xaa               | tableswitch  | 用于 switch 条件跳转，case 值连续（可变长度指令）            |
| 171              | 0xab               | lookupswitch | 用于 switch 条件跳转，case 值不连续（可变长度指令）          |
| 172              | 0xac               | ireturn      | 从当前方法返回 int                                           |
| 173              | 0xad               | lreturn      | 从当前方法返回 long                                          |
| 174              | 0xae               | freturn      | 从当前方法返回 float                                         |
| 175              | 0xaf               | dreturn      | 从当前方法返回 double                                        |
| 176              | 0xb0               | areturn      | 从当前方法返回对象引用                                       |
| 177              | 0xb1               | return       | 从当前方法返回 void                                          |

## 引用 References

| 字节码（十进制） | 字节码（十六进制） | 助记符          | 指令含义                                                     |
| ---------------- | ------------------ | --------------- | ------------------------------------------------------------ |
| 178              | 0xb2               | getstatic       | 获取指定类的静态域，并将其压入栈顶                           |
| 179              | 0xb3               | putstatic       | 为指定类的静态域赋值                                         |
| 180              | 0xb4               | getfield        | 获取指定类的实例域，并将其压入栈顶                           |
| 181              | 0xb5               | putfield        | 为指定类的实例域赋值                                         |
| 182              | 0xb6               | invokevirtual   | 调用实例方法                                                 |
| 183              | 0xb7               | invokespecial   | 调用超类构造方法，实例初始化方法，私有方法                   |
| 184              | 0xb8               | invokestatic    | 调用静态方法                                                 |
| 185              | 0xb9               | invokeinterface | 调用接口方法                                                 |
| 186              | 0xba               | invokedynamic   | 调用动态方法                                                 |
| 187              | 0xbb               | new             | 创建一个对象，并将其引用引用值压入栈顶                       |
| 188              | 0xbc               | newarray        | 创建一个指定的原始类型（如 int，float，char 等）的数组，并将其引用值压入栈顶 |
| 189              | 0xbd               | anewarray       | 创建一个引用型（如类，接口，数组）的数组，并将其引用值压入栈顶 |
| 190              | 0xbe               | arraylength     | 获取数组的长度值并压入栈顶                                   |
| 191              | 0xbf               | athrow          | 将栈顶的异常抛出                                             |
| 192              | 0xc0               | checkcast       | 检验类型转换，检验未通过将抛出 ClassCastException            |
| 193              | 0xc1               | instanceof      | 检验对象是否是指定类的实际，如果是将 1 压入栈顶，否则将 0 压入栈顶 |
| 194              | 0xc2               | monitorenter    | 获得对象的锁，用于同步方法或同步块                           |
| 195              | 0xc3               | monitorexit     | 释放对象的锁，用于同步方法或同步块                           |

## 扩展 Extended

| 字节码（十进制） | 字节码（十六进制） | 助记符         | 指令含义                                                     |
| ---------------- | ------------------ | -------------- | ------------------------------------------------------------ |
| 196              | 0xc4               | wide           | 扩展本地变量的宽度                                           |
| 197              | 0xc5               | multianewarray | 创建指定类型和指定维度的多维数组（执行该指令时，操作栈中必须包含各维度的长度值），并将其引用压入栈顶 |
| 198              | 0xc6               | ifnull         | 为 null 时跳转                                               |
| 199              | 0xc7               | ifnonnull      | 不为 null 时跳转                                             |
| 200              | 0xc8               | goto_w         | 无条件跳转（宽索引）                                         |
| 201              | 0xc9               | jsr_w          | 跳转至指定的 32 位 offset 位置，并将 jsr_w 的下一条指令地址压入栈顶 |

## 保留 Reserved

| 字节码（十进制） | 字节码（十六进制） | 助记符     | 指令含义           |
| ---------------- | ------------------ | ---------- | ------------------ |
| 202              | 0xca               | breakpoint | 调试断点           |
| 254              | 0xfe               | impdep1    | 保留指令，暂未使用 |
| 255              | 0xff               | impdep2    | 保留指令，暂未使用 |
